scalegpt/__init__.py
scalegpt/dataset/__init__.py
scalegpt/dataset/dataloader.py
scalegpt/dataset/shardmanager.py
scalegpt/dataset/tokenizer.py
scalegpt/dataset/utils.py
scalegpt/metrics/__init__.py
scalegpt/metrics/hellaswag.py
scalegpt/models/__init__.py
scalegpt/models/_modules.py
scalegpt/models/gpt.py
scalegpt/models/utils.py
scalegpt/trainers/__init__.py
scalegpt/trainers/trainer.py
scalegpt-1.6.dist-info/METADATA
scalegpt-1.6.dist-info/WHEEL
scalegpt-1.6.dist-info/top_level.txt
scalegpt-1.6.dist-info/RECORD
