Metadata-Version: 2.1
Name: scalegpt
Version: 1.6
Summary: Scalable GPT implementation using Distributed Data Parallel for efficient, multi-GPU training of transformer models.
Home-page: https://github.com/MatinKhajavi/GPT-from-scratch
License: MIT
Classifier: Programming Language :: Python :: 3.12
Classifier: Environment :: Console
Classifier: Framework :: Jupyter
Classifier: License :: OSI Approved :: MIT License
Classifier: Natural Language :: English
Classifier: Operating System :: MacOS :: MacOS X
Classifier: Operating System :: Microsoft :: Windows
Classifier: Operating System :: POSIX :: Linux
Requires-Dist: datasets >=2.20.0
Requires-Dist: numpy ==1.26.4
Requires-Dist: Requests >=2.31.0
Requires-Dist: tiktoken >=0.7.0
Requires-Dist: torch >=2.4.0
Requires-Dist: tqdm >=4.66.4
Requires-Dist: matplotlib >=3.9.1
Requires-Dist: seaborn >=0.12.2
